MANIFEST.in
README.md
setup.py
mir/__init__.py
mir/__main__.py
mir/cli.py
mir/main.py
mir/version.py
mir/commands/__init__.py
mir/commands/base.py
mir/commands/branch.py
mir/commands/checkout.py
mir/commands/commit.py
mir/commands/exporting.py
mir/commands/filter.py
mir/commands/importing.py
mir/commands/init.py
mir/commands/log.py
mir/commands/merge.py
mir/commands/mining.py
mir/commands/reset.py
mir/commands/status.py
mir/commands/training.py
mir/conf/__init__.py
mir/conf/mining-template.yaml
mir/conf/training-template.yaml
mir/scm/__init__.py
mir/scm/base.py
mir/scm/cmd.py
mir/tools/__init__.py
mir/tools/annotations.py
mir/tools/checker.py
mir/tools/code.py
mir/tools/data_exporter.py
mir/tools/exodus.py
mir/tools/hash_utils.py
mir/tools/metadatas.py
mir/tools/mir_repo_utils.py
mir/tools/mir_storage.py
mir/tools/mir_storage_ops.py
mir/tools/revs_parser.py
mir/tools/utils.py
pymir.egg-info/PKG-INFO
pymir.egg-info/SOURCES.txt
pymir.egg-info/dependency_links.txt
pymir.egg-info/entry_points.txt
pymir.egg-info/requires.txt
pymir.egg-info/top_level.txt
ymir_proto/__init__.py
ymir_proto/gen/__init__.py
ymir_proto/gen/mir_common_pb2.py
ymir_proto/gen/mir_controller_service_pb2.py
ymir_proto/gen/mir_controller_service_pb2_grpc.py
ymir_proto/gen/mir_entities_pb2.py
ymir_proto/ids/type_id_names.csv
ymir_proto/util/__init__.py
ymir_proto/util/ids.py
ymir_proto/util/task_util.py